mkdocstrings_handlers/github/__init__.py
mkdocstrings_handlers/github/config.py
mkdocstrings_handlers/github/handler.py
mkdocstrings_handlers/github/objects.py
mkdocstrings_handlers/github/py.typed
mkdocstrings_handlers/github/rendering.py
mkdocstrings_handlers/github/templates/material/_macros.html.jinja
mkdocstrings_handlers/github/templates/material/action.html.jinja
mkdocstrings_handlers/github/templates/material/heading.html.jinja
mkdocstrings_handlers/github/templates/material/inputs.html.jinja
mkdocstrings_handlers/github/templates/material/outputs.html.jinja
mkdocstrings_handlers/github/templates/material/secrets.html.jinja
mkdocstrings_handlers/github/templates/material/style.css
mkdocstrings_handlers/github/templates/material/workflow.html.jinja
mkdocstrings_github-0.6.3.dist-info/METADATA
mkdocstrings_github-0.6.3.dist-info/WHEEL
mkdocstrings_github-0.6.3.dist-info/licenses/LICENSE
mkdocstrings_github-0.6.3.dist-info/RECORD
