Metadata-Version: 2.4
Name: mkdocstrings-github
Version: 0.6.3
Summary: A GitHub Action handler for mkdocstrings
Author-email: Mark Hu <watermarkhu@gmail.com>
License: MIT
License-File: LICENSE
Classifier: Development Status :: 4 - Beta
Classifier: Intended Audience :: Developers
Classifier: Programming Language :: Python
Classifier: Programming Language :: Python :: 3
Classifier: Programming Language :: Python :: 3 :: Only
Classifier: Programming Language :: Python :: 3.10
Classifier: Programming Language :: Python :: 3.11
Classifier: Programming Language :: Python :: 3.12
Classifier: Programming Language :: Python :: 3.13
Classifier: Programming Language :: Python :: 3.14
Classifier: Topic :: Documentation
Classifier: Topic :: Software Development
Classifier: Topic :: Software Development :: Documentation
Classifier: Topic :: Utilities
Classifier: Typing :: Typed
Requires-Python: <3.15,>=3.10
Requires-Dist: gitpython<4,>=3.1.45
Requires-Dist: mkdocstrings<2,>=1
Requires-Dist: ruamel-yaml<1,>=0.18.16
Requires-Dist: typing-extensions>=4.0; python_version < '3.11'
